FridaZhongwenWendang/README.md
FridaZhongwenWendang/__init__.py
FridaZhongwenWendang/__main__.py
FridaZhongwenWendang/file.epub
FridaZhongwenWendang/index.html
FridaZhongwenWendang/css/__init__.py
FridaZhongwenWendang/css/annotations.css
FridaZhongwenWendang/css/main.css
FridaZhongwenWendang/css/normalize.css
FridaZhongwenWendang/css/popup.css
FridaZhongwenWendang/font/__init__.py
FridaZhongwenWendang/font/fontello.eot
FridaZhongwenWendang/font/fontello.svg
FridaZhongwenWendang/font/fontello.ttf
FridaZhongwenWendang/font/fontello.woff
FridaZhongwenWendang/img/__init__.py
FridaZhongwenWendang/img/annotator-glyph-sprite.png
FridaZhongwenWendang/img/annotator-icon-sprite.png
FridaZhongwenWendang/img/apple-touch-icon.png
FridaZhongwenWendang/img/cancelfullscreen.png
FridaZhongwenWendang/img/close.png
FridaZhongwenWendang/img/fullscreen.png
FridaZhongwenWendang/img/loader.gif
FridaZhongwenWendang/img/menu-icon.png
FridaZhongwenWendang/img/save.png
FridaZhongwenWendang/img/saved.png
FridaZhongwenWendang/img/settings-s.png
FridaZhongwenWendang/img/settings.png
FridaZhongwenWendang/img/star.png
FridaZhongwenWendang/js/__init__.py
FridaZhongwenWendang/js/epub.js
FridaZhongwenWendang/js/epub.min.js
FridaZhongwenWendang/js/epub.min.map
FridaZhongwenWendang/js/hooks.min.js
FridaZhongwenWendang/js/hooks.min.map
FridaZhongwenWendang/js/reader.js
FridaZhongwenWendang/js/reader.js.map
FridaZhongwenWendang/js/reader.min.js
FridaZhongwenWendang/js/reader.min.map
FridaZhongwenWendang/js/hooks/__init__.py
FridaZhongwenWendang/js/hooks/extensions/__init__.py
FridaZhongwenWendang/js/hooks/extensions/highlight.js
FridaZhongwenWendang/js/libs/__init__.py
FridaZhongwenWendang/js/libs/jquery.min.js
FridaZhongwenWendang/js/libs/localforage.min.js
FridaZhongwenWendang/js/libs/screenfull.js
FridaZhongwenWendang/js/libs/screenfull.min.js
FridaZhongwenWendang/js/libs/zip.min.js
FridaZhongwenWendang/js/plugins/__init__.py
FridaZhongwenWendang/js/plugins/hypothesis.js
frida_zhongwen_wendang-2024.3.3.0.dist-info/METADATA
frida_zhongwen_wendang-2024.3.3.0.dist-info/WHEEL
frida_zhongwen_wendang-2024.3.3.0.dist-info/entry_points.txt
frida_zhongwen_wendang-2024.3.3.0.dist-info/top_level.txt
frida_zhongwen_wendang-2024.3.3.0.dist-info/RECORD
